palmettopy/__init__.py
palmettopy/exceptions.py
palmettopy/fastcoherence.py
palmettopy/palmetto.py
palmettopy-3.3.dist-info/LICENSE.txt
palmettopy-3.3.dist-info/METADATA
palmettopy-3.3.dist-info/WHEEL
palmettopy-3.3.dist-info/top_level.txt
palmettopy-3.3.dist-info/RECORD
