Metadata-Version: 2.1
Name: palmettopy
Version: 3.3
Summary: Palmetto Python Interface
Home-page: https://github.com/dice-group/palmetto-py
Author: Ivan Ermilov
Author-email: ivan.s.ermilov@gmail.com
License: UNKNOWN
Keywords: aksw,nlp,semantic-web,dice-research,topic modeling,topic coherence
Platform: UNKNOWN
License-File: LICENSE.txt
Requires-Dist: requests
